<?xml version="1.0" ?>
<channels>
  <channel site="tvpassport.com" lang="en" xmltv_id="KABCDT1.us" site_id="CH_K">KABCDT1.us</channel>
  <channel site="tvpassport.com" lang="en" xmltv_id="KCBSDT1.us" site_id="CH_K">KCBSDT1.us</channel>
  <channel site="tvpassport.com" lang="en" xmltv_id="KCNCDT1.us" site_id="CH_K">KCNCDT1.us</channel>
  <channel site="tvpassport.com" lang="en" xmltv_id="KDVRDT1.us" site_id="CH_K">KDVRDT1.us</channel>
  <channel site="tvpassport.com" lang="en" xmltv_id="KGTVDT1.us" site_id="CH_K">KGTVDT1.us</channel>
  <channel site="tvpassport.com" lang="en" xmltv_id="KHONDT1.us" site_id="CH_K">KHONDT1.us</channel>
  <channel site="tvpassport.com" lang="en" xmltv_id="KBIMDT1.us" site_id="CH_K">KBIMDT1.us</channel>
  <channel site="tvpassport.com" lang="en" xmltv_id="KSBWDT1.us" site_id="CH_K">KSBWDT1.us</channel>
  <channel site="tvpassport.com" lang="en" xmltv_id="KSEEDT1.us" site_id="CH_K">KSEEDT1.us</channel>
  <channel site="tvpassport.com" lang="en" xmltv_id="KTVIDT1.us" site_id="CH_K">KTVIDT1.us</channel>
  <channel site="tvpassport.com" lang="en" xmltv_id="KTVTDT1.us" site_id="CH_K">KTVTDT1.us</channel>
  <channel site="tvpassport.com" lang="en" xmltv_id="WAVEDT1.us" site_id="CH_K">WAVEDT1.us</channel>
  <channel site="tvpassport.com" lang="en" xmltv_id="WBBHDT1.us" site_id="CH_K">WBBHDT1.us</channel>
  <channel site="tvpassport.com" lang="en" xmltv_id="WBMALD1.us" site_id="CH_K">WBMALD1.us</channel>
  <channel site="tvpassport.com" lang="en" xmltv_id="WBRCDT1.us" site_id="CH_K">WBRCDT1.us</channel>
  <channel site="tvpassport.com" lang="en" xmltv_id="WBZDT1.us" site_id="CH_K">WBZDT1.us</channel>
  <channel site="tvpassport.com" lang="en" xmltv_id="WCAUDT1.us" site_id="CH_K">WCAUDT1.us</channel>
  <channel site="tvpassport.com" lang="en" xmltv_id="WCCODT1.us" site_id="CH_K">WCCODT1.us</channel>
  <channel site="tvpassport.com" lang="en" xmltv_id="WCJBDT1.us" site_id="CH_K">WCJBDT1.us</channel>
  <channel site="tvpassport.com" lang="en" xmltv_id="WCVBDT1.us" site_id="CH_K">WCVBDT1.us</channel>
  <channel site="tvpassport.com" lang="en" xmltv_id="WDBDDT1.us" site_id="CH_K">WDBDDT1.us</channel>
  <channel site="tvpassport.com" lang="en" xmltv_id="WDFXDT1.us" site_id="CH_K">WDFXDT1.us</channel>
  <channel site="tvpassport.com" lang="en" xmltv_id="WDIVDT1.us" site_id="CH_K">WDIVDT1.us</channel>
  <channel site="tvpassport.com" lang="en" xmltv_id="WDRBDT1.us" site_id="CH_K">WDRBDT1.us</channel>
  <channel site="tvpassport.com" lang="en" xmltv_id="WEWSDT1.us" site_id="CH_K">WEWSDT1.us</channel>
  <channel site="tvpassport.com" lang="en" xmltv_id="WFFTDT1.us" site_id="CH_K">WFFTDT1.us</channel>
  <channel site="tvpassport.com" lang="en" xmltv_id="WFORDT1.us" site_id="CH_K">WFORDT1.us</channel>
  <channel site="tvpassport.com" lang="en" xmltv_id="WFOXDT1.us" site_id="CH_K">WFOXDT1.us</channel>
  <channel site="tvpassport.com" lang="en" xmltv_id="WFXGDT1.us" site_id="CH_K">WFXGDT1.us</channel>
  <channel site="tvpassport.com" lang="en" xmltv_id="WFXRDT1.us" site_id="CH_K">WFXRDT1.us</channel>
  <channel site="tvpassport.com" lang="en" xmltv_id="WGCLDT1.us" site_id="CH_K">WGCLDT1.us</channel>
  <channel site="tvpassport.com" lang="en" xmltv_id="WGXADT1.us" site_id="CH_K">WGXADT1.us</channel>
  <channel site="tvpassport.com" lang="en" xmltv_id="WINKDT1.us" site_id="CH_K">WINKDT1.us</channel>
  <channel site="tvpassport.com" lang="en" xmltv_id="WIVBDT1.us" site_id="CH_K">WIVBDT1.us</channel>
  <channel site="tvpassport.com" lang="en" xmltv_id="WJTVDT1.us" site_id="CH_K">WJTVDT1.us</channel>
  <channel site="tvpassport.com" lang="en" xmltv_id="WKBWDT1.us" site_id="CH_K">WKBWDT1.us</channel>
  <channel site="tvpassport.com" lang="en" xmltv_id="WKRGDT1.us" site_id="CH_K">WKRGDT1.us</channel>
  <channel site="tvpassport.com" lang="en" xmltv_id="WKRNDT1.us" site_id="CH_K">WKRNDT1.us</channel>
  <channel site="tvpassport.com" lang="en" xmltv_id="WKYTDT1.us" site_id="CH_K">WKYTDT1.us</channel>
  <channel site="tvpassport.com" lang="en" xmltv_id="WLBTDT1.us" site_id="CH_K">WLBTDT1.us</channel>
  <channel site="tvpassport.com" lang="en" xmltv_id="WLKYDT1.us" site_id="CH_K">WLKYDT1.us</channel>
  <channel site="tvpassport.com" lang="en" xmltv_id="WMCDT1.us" site_id="CH_K">WMCDT1.us</channel>
  <channel site="tvpassport.com" lang="en" xmltv_id="WNBCDT1.us" site_id="CH_K">WNBCDT1.us</channel>
  <channel site="tvpassport.com" lang="en" xmltv_id="WNLODT1.us" site_id="CH_K">WNLODT1.us</channel>
  <channel site="tvpassport.com" lang="en" xmltv_id="WOAIDT1.us" site_id="CH_K">WOAIDT1.us</channel>
  <channel site="tvpassport.com" lang="en" xmltv_id="WOFLDT1.us" site_id="CH_K">WOFLDT1.us</channel>
  <channel site="tvpassport.com" lang="en" xmltv_id="WPGHDT1.us" site_id="CH_K">WPGHDT1.us</channel>
  <channel site="tvpassport.com" lang="en" xmltv_id="WPMIDT1.us" site_id="CH_K">WPMIDT1.us</channel>
  <channel site="tvpassport.com" lang="en" xmltv_id="WPVIDT1.us" site_id="CH_K">WPVIDT1.us</channel>
  <channel site="tvpassport.com" lang="en" xmltv_id="WRCDT1.us" site_id="CH_K">WRCDT1.us</channel>
  <channel site="tvpassport.com" lang="en" xmltv_id="WRDWDT1.us" site_id="CH_K">WRDWDT1.us</channel>
  <channel site="tvpassport.com" lang="en" xmltv_id="WSBTDT1.us" site_id="CH_K">WSBTDT1.us</channel>
  <channel site="tvpassport.com" lang="en" xmltv_id="WSHMLD1.us" site_id="CH_K">WSHMLD1.us</channel>
  <channel site="tvpassport.com" lang="en" xmltv_id="WSMVDT1.us" site_id="CH_K">WSMVDT1.us</channel>
  <channel site="tvpassport.com" lang="en" xmltv_id="WSVNDT2.us" site_id="CH_K">WSVNDT2.us</channel>
  <channel site="tvpassport.com" lang="en" xmltv_id="WSVNDT1.us" site_id="CH_K">WSVNDT1.us</channel>
  <channel site="tvpassport.com" lang="en" xmltv_id="WTAEDT1.us" site_id="CH_K">WTAEDT1.us</channel>
  <channel site="tvpassport.com" lang="en" xmltv_id="WTENDT1.us" site_id="CH_K">WTENDT1.us</channel>
  <channel site="tvpassport.com" lang="en" xmltv_id="WTLVDT1.us" site_id="CH_K">WTLVDT1.us</channel>
  <channel site="tvpassport.com" lang="en" xmltv_id="WTNZDT1.us" site_id="CH_K">WTNZDT1.us</channel>
  <channel site="tvpassport.com" lang="en" xmltv_id="WTOCDT1.us" site_id="CH_K">WTOCDT1.us</channel>
  <channel site="tvpassport.com" lang="en" xmltv_id="WTVJDT1.us" site_id="CH_K">WTVJDT1.us</channel>
  <channel site="tvpassport.com" lang="en" xmltv_id="WTVYDT1.us" site_id="CH_K">WTVYDT1.us</channel>
  <channel site="tvpassport.com" lang="en" xmltv_id="WTVYDT4.us" site_id="CH_K">WTVYDT4.us</channel>
  <channel site="tvpassport.com" lang="en" xmltv_id="WTWCDT1.us" site_id="CH_K">WTWCDT1.us</channel>
  <channel site="tvpassport.com" lang="en" xmltv_id="WUTVDT1.us" site_id="CH_K">WUTVDT1.us</channel>
  <channel site="tvpassport.com" lang="en" xmltv_id="WVUEDT1.us" site_id="CH_K">WVUEDT1.us</channel>
  <channel site="tvpassport.com" lang="en" xmltv_id="WVLADT1.us" site_id="CH_K">WVLADT1.us</channel>
  <channel site="tvpassport.com" lang="en" xmltv_id="WVTMDT1.us" site_id="CH_K">WVTMDT1.us</channel>
  <channel site="tvpassport.com" lang="en" xmltv_id="WWBTDT1.us" site_id="CH_K">WWBTDT1.us</channel>
  <channel site="tvpassport.com" lang="en" xmltv_id="WWLPDT1.us" site_id="CH_K">WWLPDT1.us</channel>
  <channel site="tvpassport.com" lang="en" xmltv_id="WXINDT1.us" site_id="CH_K">WXINDT1.us</channel>
  <channel site="tvpassport.com" lang="en" xmltv_id="WXYZDT1.us" site_id="CH_K">WXYZDT1.us</channel>
  <channel site="tvpassport.com" lang="en" xmltv_id="WZTVDT1.us" site_id="CH_K">WZTVDT1.us</channel>
</channels>
